wikipedia/__init__.py
wikipedia/exceptions.py
wikipedia/parsers.py
wikipedia/util.py
wikipedia/wikipedia.py
nlpia2_wikipedia-1.5.18.dist-info/LICENSE
nlpia2_wikipedia-1.5.18.dist-info/METADATA
nlpia2_wikipedia-1.5.18.dist-info/WHEEL
nlpia2_wikipedia-1.5.18.dist-info/RECORD
