Metadata-Version: 2.1
Name: nlpia2_wikipedia
Version: 1.5.18
Summary: Updated version of `wikipedia` package because original repo has been abandoned since 2014.
Home-page: https://gitlab.com/tangibleai/community/nlpia2-wikipedia
License: AGPL-3.0-or-later
Keywords: Wikipedia,Wikimedia,WikiData,WikiText,wiki,API,scraping,wrapper,crawler,html
Author: Hobson Lane
Author-email: hobson@tangibleai.com
Requires-Python: >=3.8
Classifier: Development Status :: 5 - Production/Stable
Classifier: Intended Audience :: Developers
Classifier: License :: OSI Approved :: GNU Affero General Public License v3 or later (AGPLv3+)
Classifier: Natural Language :: English
Classifier: Operating System :: OS Independent
Classifier: Programming Language :: Python :: 3
Classifier: Programming Language :: Python :: 3.8
Classifier: Programming Language :: Python :: 3.9
Classifier: Programming Language :: Python :: 3.10
Classifier: Programming Language :: Python :: 3.11
Classifier: Programming Language :: Python :: 3.12
Classifier: Programming Language :: Python :: 3.13
Classifier: Topic :: Internet :: WWW/HTTP :: Dynamic Content :: Wiki
Classifier: Topic :: Software Development :: Libraries :: Python Modules
Classifier: Topic :: Text Processing :: Linguistic
Requires-Dist: beautifulsoup4 (>=4.12,<5.0)
Requires-Dist: pandas (>=2.1.4,<3.0.0)
Requires-Dist: poetry (>=1.1)
Requires-Dist: requests (>=2.30.0,<3.0.0)
Project-URL: Documentation, https://gitlab.com/tangibleai/community/nlpia2-wikipedia
Project-URL: Repository, https://gitlab.com/tangibleai/community/nlpia2-wikipedia
